arachnea/__init__.py
arachnea/arachnea.py
arachnea/arachnea_test.py
arachnea-0.0.5.dist-info/LICENSE
arachnea-0.0.5.dist-info/METADATA
arachnea-0.0.5.dist-info/WHEEL
arachnea-0.0.5.dist-info/top_level.txt
arachnea-0.0.5.dist-info/RECORD
