Metadata-Version: 2.1
Name: arachnea
Version: 0.0.5
Summary: A Python library for efficient array operations using a fluent API.
Home-page: https://github.com/yourusername/arachnea
Author: Suhan
Author-email: suhan01.bangera@gamil.com
License: MIT
Project-URL: Source, https://github.com/Spyder01/arachnea-python
Keywords: array operations,data processing,lightweight,Python library
Platform: UNKNOWN
Classifier: Development Status :: 3 - Alpha
Classifier: Intended Audience :: Developers
Classifier: License :: OSI Approved :: MIT License
Classifier: Programming Language :: Python :: 3
Classifier: Programming Language :: Python :: 3.9
Classifier: Programming Language :: Python :: 3.10
Classifier: Programming Language :: Python :: 3.11
